{
  "project_info": {
    "project_number": "587845765713",
    "project_id": "triviagame-89a99",
    "storage_bucket": "triviagame-89a99.appspot.com"
  },
  "client": [
    {
      "client_info": {
        "mobilesdk_app_id": "1:587845765713:android:4f07c1d210aa43b11ac670",
        "android_client_info": {
          "package_name": "com.flutterflow.fftrivia"
        }
      },
      "oauth_client": [
        {
          "client_id": "587845765713-q1fektfeckq1li1p5jtl1qrk2eqtb1n9.apps.googleusercontent.com",
          "client_type": 3
        }
      ],
      "api_key": [
        {
          "current_key": "AIzaSyCRkSqfrC2rJ_Cyr3da0TiMM6WESqY0S9s"
        }
      ],
      "services": {
        "appinvite_service": {
          "other_platform_oauth_client": [
            {
              "client_id": "587845765713-q1fektfeckq1li1p5jtl1qrk2eqtb1n9.apps.googleusercontent.com",
              "client_type": 3
            },
            {
              "client_id": "587845765713-lmka828p4hui16rubbi8vbc64pehrlko.apps.googleusercontent.com",
              "client_type": 2,
              "ios_info": {
                "bundle_id": "com.flutterflow.fftrivia"
              }
            }
          ]
        }
      }
    }
  ],
  "configuration_version": "1"
}